[
{"id": "rod_default", "name": "Bamboo Pole", "type": "Global", "description": "A simple bamboo pole. It has no special effects but gets the job done.", "base_cost": 0, "max_level": 0, "effect_per_level": 0, "cost_multiplier": 0, "biome_id": "global"},
{"id": "rod_strength", "name": "Ironwood Caster", "type": "Global", "description": "A sturdy rod reinforced with ironwood. Increases Strength.", "base_cost": 2000, "max_level": 100, "effect_per_level": "Strength +25", "cost_multiplier": 1.07, "biome_id": "global"},
{"id": "rod_luck", "name": "Fortune's Whim", "type": "Global", "description": "A rod that feels lucky in your hands. Increases Luck.", "base_cost": 10000, "max_level": 100, "effect_per_level": "Luck +25", "cost_multiplier": 1.065, "biome_id": "global"},
{"id": "rod_relic", "name": "Archaeologist's Rod", "type": "Global", "description": "Equipped with sensors for ancient materials. Increases Relic rarity weight.", "base_cost": 25000, "max_level": 100, "effect_per_level": "Relic Weight +50", "cost_multiplier": 1.05, "biome_id": "global"},
{"id": "rod_treasure", "name": "Gilded Seeker", "type": "Global", "description": "A luxurious rod that seems to attract gold. Increases Treasure Chest rarity weight.", "base_cost": 50000, "max_level": 100, "effect_per_level": "Treasure Weight +25", "cost_multiplier": 1.05, "biome_id": "global"},
{"id": "rod_biome_1", "name": "River Rod", "type": "Biome", "description": "A specialized rod crafted for the Tinker River. Increases XP gained while fishing here.", "base_cost": 124, "max_level": 50, "effect_per_level": "XP +2.5%", "cost_multiplier": 1.122, "biome_id": 1},
{"id": "rod_biome_2", "name": "Lake Line", "type": "Biome", "description": "A specialized rod crafted for the Misty Pine Lake. Increases XP gained while fishing here.", "base_cost": 124, "max_level": 50, "effect_per_level": "XP +2.5%", "cost_multiplier": 1.124, "biome_id": 2},
{"id": "rod_biome_3", "name": "Coast Rod", "type": "Biome", "description": "A specialized rod crafted for the Sapphire Coast. Increases XP gained while fishing here.", "base_cost": 132, "max_level": 50, "effect_per_level": "XP +2.5%", "cost_multiplier": 1.123, "biome_id": 3},
{"id": "rod_biome_4", "name": "Bay Staff", "type": "Biome", "description": "A specialized rod crafted for the Thundercliff Bay. Increases XP gained while fishing here.", "base_cost": 132, "max_level": 50, "effect_per_level": "XP +2.5%", "cost_multiplier": 1.124, "biome_id": 4},
{"id": "rod_biome_5", "name": "Grotto Rod", "type": "Biome", "description": "A specialized rod crafted for the Stoneheart Grotto. Increases XP gained while fishing here.", "base_cost": 140, "max_level": 50, "effect_per_level": "XP +2.5%", "cost_multiplier": 1.124, "biome_id": 5},
{"id": "rod_biome_6", "name": "Frosthollow Rod", "type": "Biome", "description": "A specialized rod crafted for the Frosthollow Fjord. Increases XP gained while fishing here.", "base_cost": 140, "max_level": 50, "effect_per_level": "XP +2.5%", "cost_multiplier": 1.125, "biome_id": 6},
{"id": "rod_biome_7", "name": "River Fisher", "type": "Biome", "description": "A specialized rod crafted for the Verdant Canopy River. Increases XP gained while fishing here.", "base_cost": 148, "max_level": 50, "effect_per_level": "XP +2.5%", "cost_multiplier": 1.124, "biome_id": 7},
{"id": "rod_biome_8", "name": "Flow Rod", "type": "Biome", "description": "A specialized rod crafted for the Obsidian Flow River. Increases XP gained while fishing here.", "base_cost": 148, "max_level": 50, "effect_per_level": "XP +2.5%", "cost_multiplier": 1.125, "biome_id": 8},
{"id": "rod_biome_9", "name": "Caldera Line", "type": "Biome", "description": "A specialized rod crafted for the Infernal Caldera. Increases XP gained while fishing here.", "base_cost": 156, "max_level": 50, "effect_per_level": "XP +2.5%", "cost_multiplier": 1.125, "biome_id": 9},
{"id": "rod_biome_10", "name": "Basin Wand", "type": "Biome", "description": "A specialized rod crafted for the Primordial Basin. Increases XP gained while fishing here.", "base_cost": 156, "max_level": 50, "effect_per_level": "XP +2.5%", "cost_multiplier": 1.126, "biome_id": 10},
{"id": "rod_biome_11", "name": "Harbor Seeker", "type": "Biome", "description": "A specialized rod crafted for the The Drowned Harbor. Increases XP gained while fishing here.", "base_cost": 164, "max_level": 50, "effect_per_level": "XP +2.5%", "cost_multiplier": 1.125, "biome_id": 11},
{"id": "rod_biome_12", "name": "Canal Caster", "type": "Biome", "description": "A specialized rod crafted for the The Grand Canal. Increases XP gained while fishing here.", "base_cost": 164, "max_level": 50, "effect_per_level": "XP +2.5%", "cost_multiplier": 1.126, "biome_id": 12},
{"id": "rod_biome_13", "name": "Aethelgard Wand", "type": "Biome", "description": "A specialized rod crafted for the Sunken City of Aethelgard. Increases XP gained while fishing here.", "base_cost": 172, "max_level": 50, "effect_per_level": "XP +2.5%", "cost_multiplier": 1.126, "biome_id": 13},
{"id": "rod_biome_14", "name": "Crystal Grip", "type": "Biome", "description": "A specialized rod crafted for the The Crystal Archives. Increases XP gained while fishing here.", "base_cost": 172, "max_level": 50, "effect_per_level": "XP +2.5%", "cost_multiplier": 1.126, "biome_id": 14},
{"id": "rod_biome_15", "name": "Deep Rod", "type": "Biome", "description": "A specialized rod crafted for the The Throne of the Deep. Increases XP gained while fishing here.", "base_cost": 180, "max_level": 50, "effect_per_level": "XP +2.5%", "cost_multiplier": 1.126, "biome_id": 15},
{"id": "rod_biome_16", "name": "Gorge Line", "type": "Biome", "description": "A specialized rod crafted for the The Cheddar Gorge. Increases XP gained while fishing here.", "base_cost": 180, "max_level": 50, "effect_per_level": "XP +2.5%", "cost_multiplier": 1.127, "biome_id": 16},
{"id": "rod_biome_17", "name": "Falls Rod", "type": "Biome", "description": "A specialized rod crafted for the Soda Pop Falls. Increases XP gained while fishing here.", "base_cost": 188, "max_level": 50, "effect_per_level": "XP +2.5%", "cost_multiplier": 1.126, "biome_id": 17},
{"id": "rod_biome_18", "name": "River Rod", "type": "Biome", "description": "A specialized rod crafted for the The Sizzle Spice River. Increases XP gained while fishing here.", "base_cost": 188, "max_level": 50, "effect_per_level": "XP +2.5%", "cost_multiplier": 1.127, "biome_id": 18},
{"id": "rod_biome_19", "name": "Baker's Hook", "type": "Biome", "description": "A specialized rod crafted for the The Baker's Bay. Increases XP gained while fishing here.", "base_cost": 196, "max_level": 50, "effect_per_level": "XP +2.5%", "cost_multiplier": 1.127, "biome_id": 19},
{"id": "rod_biome_20", "name": "Titans Wand", "type": "Biome", "description": "A specialized rod crafted for the The Banquet of Titans. Increases XP gained while fishing here.", "base_cost": 196, "max_level": 50, "effect_per_level": "XP +2.5%", "cost_multiplier": 1.127, "biome_id": 20},
{"id": "rod_biome_21", "name": "Chlorophyll Caster", "type": "Biome", "description": "A specialized rod crafted for the The Chlorophyll Canopy. Increases XP gained while fishing here.", "base_cost": 180, "max_level": 50, "effect_per_level": "XP +2.5%", "cost_multiplier": 1.132, "biome_id": 21},
{"id": "rod_biome_22", "name": "Riverbeds Line", "type": "Biome", "description": "A specialized rod crafted for the The Rooted Riverbeds. Increases XP gained while fishing here.", "base_cost": 188, "max_level": 50, "effect_per_level": "XP +2.5%", "cost_multiplier": 1.132, "biome_id": 22},
{"id": "rod_biome_23", "name": "Spore Pole", "type": "Biome", "description": "A specialized rod crafted for the The Spore Light Caverns. Increases XP gained while fishing here.", "base_cost": 196, "max_level": 50, "effect_per_level": "XP +2.5%", "cost_multiplier": 1.131, "biome_id": 23},
{"id": "rod_biome_24", "name": "Coral Fisher", "type": "Biome", "description": "A specialized rod crafted for the The Thorn Coral Gardens. Increases XP gained while fishing here.", "base_cost": 204, "max_level": 50, "effect_per_level": "XP +2.5%", "cost_multiplier": 1.131, "biome_id": 24},
{"id": "rod_biome_25", "name": "Blossom Rod", "type": "Biome", "description": "A specialized rod crafted for the The Blossom Basin. Increases XP gained while fishing here.", "base_cost": 212, "max_level": 50, "effect_per_level": "XP +2.5%", "cost_multiplier": 1.131, "biome_id": 25},
{"id": "rod_biome_26", "name": "Pools Caster", "type": "Biome", "description": "A specialized rod crafted for the The Paleolithic Pools. Increases XP gained while fishing here.", "base_cost": 220, "max_level": 50, "effect_per_level": "XP +2.5%", "cost_multiplier": 1.128, "biome_id": 26},
{"id": "rod_biome_27", "name": "Totem Grip", "type": "Biome", "description": "A specialized rod crafted for the The Totem Atoll. Increases XP gained while fishing here.", "base_cost": 228, "max_level": 50, "effect_per_level": "XP +2.5%", "cost_multiplier": 1.128, "biome_id": 27},
{"id": "rod_biome_28", "name": "Cenote Hook", "type": "Biome", "description": "A specialized rod crafted for the The Sun Gold Cenote. Increases XP gained while fishing here.", "base_cost": 236, "max_level": 50, "effect_per_level": "XP +2.5%", "cost_multiplier": 1.128, "biome_id": 28},
{"id": "rod_biome_29", "name": "Lantern Caster", "type": "Biome", "description": "A specialized rod crafted for the The Jade Lantern Lake. Increases XP gained while fishing here.", "base_cost": 244, "max_level": 50, "effect_per_level": "XP +2.5%", "cost_multiplier": 1.128, "biome_id": 29},
{"id": "rod_biome_30", "name": "Fjords Hook", "type": "Biome", "description": "A specialized rod crafted for the The Runic Fjords. Increases XP gained while fishing here.", "base_cost": 260, "max_level": 50, "effect_per_level": "XP +2.5%", "cost_multiplier": 1.129, "biome_id": 30},
{"id": "rod_biome_31", "name": "Delta Caster", "type": "Biome", "description": "A specialized rod crafted for the The Steam Forge Delta. Increases XP gained while fishing here.", "base_cost": 276, "max_level": 50, "effect_per_level": "XP +2.5%", "cost_multiplier": 1.129, "biome_id": 31},
{"id": "rod_biome_32", "name": "Dockyards Hook", "type": "Biome", "description": "A specialized rod crafted for the The Diesel Dredge Dockyards. Increases XP gained while fishing here.", "base_cost": 292, "max_level": 50, "effect_per_level": "XP +2.5%", "cost_multiplier": 1.13, "biome_id": 32},
{"id": "rod_biome_33", "name": "Neon Hook", "type": "Biome", "description": "A specialized rod crafted for the The Neon Grid Reef. Increases XP gained while fishing here.", "base_cost": 308, "max_level": 50, "effect_per_level": "XP +2.5%", "cost_multiplier": 1.13, "biome_id": 33},
{"id": "rod_biome_34", "name": "Nuclear Rod", "type": "Biome", "description": "A specialized rod crafted for the The Nuclear Abyssal Reactor. Increases XP gained while fishing here.", "base_cost": 324, "max_level": 50, "effect_per_level": "XP +2.5%", "cost_multiplier": 1.131, "biome_id": 34},
{"id": "rod_biome_35", "name": "Nanotech Staff", "type": "Biome", "description": "A specialized rod crafted for the The Nanotech Singularity. Increases XP gained while fishing here.", "base_cost": 340, "max_level": 50, "effect_per_level": "XP +2.5%", "cost_multiplier": 1.131, "biome_id": 35},
{"id": "rod_biome_36", "name": "Aether Wand", "type": "Biome", "description": "A specialized rod crafted for the The Aether Flux Stream. Increases XP gained while fishing here.", "base_cost": 356, "max_level": 50, "effect_per_level": "XP +2.5%", "cost_multiplier": 1.131, "biome_id": 36},
{"id": "rod_biome_37", "name": "Grotto Seeker", "type": "Biome", "description": "A specialized rod crafted for the The Gravity Well Grotto. Increases XP gained while fishing here.", "base_cost": 372, "max_level": 50, "effect_per_level": "XP +2.5%", "cost_multiplier": 1.132, "biome_id": 37},
{"id": "rod_biome_38", "name": "Estuary Rod", "type": "Biome", "description": "A specialized rod crafted for the The Ectoplasmic Estuary. Increases XP gained while fishing here.", "base_cost": 388, "max_level": 50, "effect_per_level": "XP +2.5%", "cost_multiplier": 1.132, "biome_id": 38},
{"id": "rod_biome_39", "name": "Expanse Caster", "type": "Biome", "description": "A specialized rod crafted for the The Cosmic Void Expanse. Increases XP gained while fishing here.", "base_cost": 404, "max_level": 50, "effect_per_level": "XP +2.5%", "cost_multiplier": 1.132, "biome_id": 39},
{"id": "rod_biome_40", "name": "Reality Hook", "type": "Biome", "description": "A specialized rod crafted for the The Reality Rift Reef. Increases XP gained while fishing here.", "base_cost": 420, "max_level": 50, "effect_per_level": "XP +2.5%", "cost_multiplier": 1.133, "biome_id": 40}
]